{
    "nodes": [
        {
            "label": "AGREEMENT",
            "name": "협력사 ESG 지원사업 업무협약",
            "properties": {
                "type": "ESG 지원",
                "date": "2023-04-14",
                "description": "동반성장위원회와 LG이노텍 간의 ESG 지원사업 협약"
            }
        },
        {
            "label": "LOCATION",
            "name": "인천 송도",
            "properties": {
                "type": "지역",
                "country": "대한민국",
                "region": "인천"
            }
        },
        {
            "label": "EVENT",
            "name": "ESG 우수 중소기업 현판식",
            "properties": {
                "date": "2023-04-14",
                "type": "현판식",
                "description": "ESG 우수 중소기업으로 선정된 기업에 대한 현판식"
            }
        }
    ],
    "relations": [
        {
            "start_node": "동반성장위원회",
            "relationship": "SIGNED",
            "end_node": "협력사 ESG 지원사업 업무협약",
            "properties": {}
        },
        {
            "start_node": "LG이노텍",
            "relationship": "SIGNED",
            "end_node": "협력사 ESG 지원사업 업무협약",
            "properties": {}
        },
        {
            "start_node": "LG이노텍",
            "relationship": "PARTNERED_WITH",
            "end_node": "동반성장위원회",
            "properties": {
                "type": "ESG 지원사업",
                "date": "2023-04-14"
            }
        },
        {
            "start_node": "협력사 ESG 지원사업 업무협약",
            "relationship": "HELD_IN",
            "end_node": "인천 송도",
            "properties": {}
        },
        {
            "start_node": "에이피텍",
            "relationship": "PARTICIPATED_IN",
            "end_node": "ESG 우수 중소기업 현판식",
            "properties": {}
        },
        {
            "start_node": "LG이노텍",
            "relationship": "SUPPLIES",
            "end_node": "에이피텍",
            "properties": {
                "product": "핸드폰 카메라 모듈 생산 설비"
            }
        }
    ]
}